{
  "providers": {
    "awscloudformation": {
      "AuthRoleName": "amplify-belleviecolleagues-dev-164130-authRole",
      "UnauthRoleArn": "arn:aws:iam::245111508555:role/amplify-belleviecolleagues-dev-164130-unauthRole",
      "AuthRoleArn": "arn:aws:iam::245111508555:role/amplify-belleviecolleagues-dev-164130-authRole",
      "Region": "eu-west-2",
      "DeploymentBucketName": "amplify-belleviecolleagues-dev-164130-deployment",
      "UnauthRoleName": "amplify-belleviecolleagues-dev-164130-unauthRole",
      "StackName": "amplify-belleviecolleagues-dev-164130",
      "StackId": "arn:aws:cloudformation:eu-west-2:245111508555:stack/amplify-belleviecolleagues-dev-164130/2d5e0bf0-5f2c-11eb-b1e6-0a4625f9b43e",
      "AmplifyAppId": "d3ihtjzvgz37vw"
    }
  },
  "auth": {
    "BelleVieColleagues": {
      "service": "Cognito",
      "providerPlugin": "awscloudformation",
      "dependsOn": [],
      "customAuth": false,
      "output": {
        "AppClientSecret": "1djbv82mqf77r5ohabq43moe5792osdt4ov6af2bo30suf8cr0pg",
        "UserPoolId": "eu-west-2_0kRHRARus",
        "AppClientIDWeb": "7shbgq6ai5jdr0s0obk10r7826",
        "AppClientID": "2bu3hs7iigub3o93r91pdbj2it",
        "HostedUIDomain": "5d7cl01ksw3s-dev",
        "IdentityPoolId": "eu-west-2:96e65376-1915-44d2-b075-5f737a78f9de",
        "IdentityPoolName": "testAuthIdentityPool__dev",
        "OAuthMetadata": "{\"AllowedOAuthFlows\":[\"code\"],\"AllowedOAuthScopes\":[\"phone\",\"email\",\"openid\",\"profile\",\"aws.cognito.signin.user.admin\"],\"CallbackURLs\":[\"http://localhost:3000/\"],\"LogoutURLs\":[\"http://localhost:3000/\"]}",
        "UserPoolName": "BelleVieColleagues"
      },
      "lastPushTimeStamp": "2021-01-25T18:59:10.616Z",
      "providerMetadata": {
        "s3TemplateURL": "https://s3.amazonaws.com/amplify-belleviecolleagues-dev-164130-deployment/amplify-cfn-templates/auth/BelleVieColleagues-cloudformation-template.yml",
        "logicalId": "authBelleVieColleagues"
      },
      "lastPushDirHash": "BNOit7i6/CyjYf5YxVX6TcztH2I="
    }
  }
}